bdtsim/__init__.py
bdtsim/account.py
bdtsim/contract.py
bdtsim/funds_diff_collection.py
bdtsim/protocol_path.py
bdtsim/simulation.py
bdtsim/cli/__init__.py
bdtsim/cli/command_manager.py
bdtsim/cli/environment_info.py
bdtsim/cli/list_data_providers.py
bdtsim/cli/list_environments.py
bdtsim/cli/list_output_formats.py
bdtsim/cli/list_protocols.py
bdtsim/cli/main.py
bdtsim/cli/run.py
bdtsim/data_provider/__init__.py
bdtsim/data_provider/data_provider.py
bdtsim/data_provider/data_provider_manager.py
bdtsim/data_provider/file_data_provider.py
bdtsim/data_provider/random_data_provider.py
bdtsim/environment/__init__.py
bdtsim/environment/environment.py
bdtsim/environment/environment_manager.py
bdtsim/environment/funds_diff_trace_mixin.py
bdtsim/environment/pyevm.py
bdtsim/environment/web3_environments.py
bdtsim/output/__init__.py
bdtsim/output/graphviz_dot.py
bdtsim/output/human_readable.py
bdtsim/output/json.py
bdtsim/output/output_format.py
bdtsim/output/output_format_manager.py
bdtsim/output/result_collector.py
bdtsim/output/simulation_result.py
bdtsim/output/yaml.py
bdtsim/protocol/__init__.py
bdtsim/protocol/exceptions.py
bdtsim/protocol/protocol.py
bdtsim/protocol/protocol_manager.py
bdtsim/protocol/fairswap/FairFileSale-reusable.sol
bdtsim/protocol/fairswap/FairFileSale.tpl.sol
bdtsim/protocol/fairswap/README.md
bdtsim/protocol/fairswap/__init__.py
bdtsim/protocol/fairswap/encoding.py
bdtsim/protocol/fairswap/fairswap.py
bdtsim/protocol/fairswap/merkle.py
bdtsim/protocol/fairswap/lEthDev-FairSwap/FairFileSale.sol
bdtsim/protocol/fairswap/lEthDev-FairSwap/README.md
bdtsim/protocol/fairswap/lEthDev-FairSwap/RepeatedFairFileSale.sol
bdtsim/protocol/optiswap/README.md
bdtsim/protocol/optiswap/__init__.py
bdtsim/protocol/optiswap/CryBtoS-OptiSwap/README.md
bdtsim/protocol/optiswap/CryBtoS-OptiSwap/fileSale.sol
bdtsim/protocol/optiswap/CryBtoS-OptiSwap/fileSaleOptimistic.sol
bdtsim/protocol/optiswap/CryBtoS-OptiSwap/fileSalePessimistic.sol
bdtsim-1.1.1.dist-info/LICENSE.md
bdtsim-1.1.1.dist-info/METADATA
bdtsim-1.1.1.dist-info/WHEEL
bdtsim-1.1.1.dist-info/entry_points.txt
bdtsim-1.1.1.dist-info/top_level.txt
bdtsim-1.1.1.dist-info/RECORD
