Metadata-Version: 2.1
Name: bdtsim
Version: 1.1.1
Summary: Blockchain Data Trading Simulator
Home-page: https://gitlab.com/MatthiasLohr/bdtsim
Author: Matthias Lohr
Author-email: mail@mlohr.com
License: Apache License 2.0
Project-URL: Documentation, https://matthiaslohr.gitlab.io/bdtsim/
Project-URL: Source, https://gitlab.com/MatthiasLohr/bdtsim
Project-URL: Tracker, https://gitlab.com/MatthiasLohr/bdtsim/issues
Platform: UNKNOWN
Classifier: Intended Audience :: Science/Research
Classifier: License :: OSI Approved :: Apache Software License
Classifier: Programming Language :: Python :: 3.7
Classifier: Programming Language :: Python :: 3.8
Classifier: Topic :: Scientific/Engineering
Requires-Python: >=3.7.*, <4
Requires-Dist: eth-tester (==0.5.0b1)
Requires-Dist: graphviz (==0.14)
Requires-Dist: hexbytes (==0.2.0)
Requires-Dist: Jinja2 (==2.11.2)
Requires-Dist: py-evm (==0.3.0a17)
Requires-Dist: py-solc-x (==0.10.1)
Requires-Dist: PyYAML (==5.3.1)
Requires-Dist: web3 (==5.11.1)
